examples/__init__.py
examples/db.py
examples/reuters.py
examples/server.py
pynorama/__init__.py
pynorama/exceptions.py
pynorama/logging.py
pynorama/make_config.py
pynorama/make_server.py
pynorama/view.py
pynorama/sessions/__init__.py
pynorama/sessions/base_store.py
pynorama/sessions/json_file.py
pynorama/sessions/memory.py
pynorama/sessions/mongo.py
pynorama/static/sw.js
pynorama/static/vendor.bundle.js
pynorama/static/view.bundle.js
pynorama/static/view.legacy.bundle.js
pynorama/static/workbox-sw.prod.v2.1.3.js
pynorama/table/__init__.py
pynorama/table/base_table.py
pynorama/table/mongo_table.py
pynorama/table/pandas_table.py
pynorama/templates/index.html
pynorama/templates/pynorama_view.html
pynorama-0.4.2.dist-info/DESCRIPTION.rst
pynorama-0.4.2.dist-info/METADATA
pynorama-0.4.2.dist-info/RECORD
pynorama-0.4.2.dist-info/WHEEL
pynorama-0.4.2.dist-info/metadata.json
pynorama-0.4.2.dist-info/top_level.txt
