Metadata-Version: 2.0
Name: pynorama
Version: 0.4.2
Summary: Natural Language Processing Visualization Tool
Home-page: https://github.com/manahl/pynorama
Author: Man AHL Technology
Author-email: ManAHLTech@ahl.com
License: LGPL-2.1
Keywords: ahl,visualization,NLP,data discovery
Platform: UNKNOWN
Classifier: Development Status :: 3 - Alpha
Classifier: Topic :: Utilities
Classifier: Framework :: Flask
Classifier: Topic :: Scientific/Engineering
Classifier: Topic :: Scientific/Engineering :: Visualization
Classifier: Programming Language :: Python
Classifier: Programming Language :: Python :: 2.7
Requires-Dist: flask
Requires-Dist: numpy
Requires-Dist: pandas
Provides-Extra: docs
Requires-Dist: pypandoc; extra == 'docs'
Requires-Dist: sphinx; extra == 'docs'
Requires-Dist: nbsphinx; extra == 'docs'
Requires-Dist: sphinxcontrib-napoleon; extra == 'docs'
Provides-Extra: examples
Requires-Dist: nltk; extra == 'examples'
Provides-Extra: mongo
Requires-Dist: pymongo; extra == 'mongo'
